boto3_mocking/__init__.py
boto3_mocking/version.py
boto3_mocking-0.1.1.dist-info/LICENSE
boto3_mocking-0.1.1.dist-info/METADATA
boto3_mocking-0.1.1.dist-info/WHEEL
boto3_mocking-0.1.1.dist-info/top_level.txt
boto3_mocking-0.1.1.dist-info/RECORD
