Metadata-Version: 2.1
Name: boto3-mocking
Version: 0.1.1
Summary: Simplify mocking AWS access through boto3
Home-page: https://github.com/rtweeks/boto3-mocking
Author: Richard T. Weeks
Author-email: rtweeks21@gmail.com
License: Apache License 2.0
Keywords: mock aws boto3 test testing
Platform: UNKNOWN
Classifier: Programming Language :: Python :: 3
Classifier: License :: OSI Approved :: MIT License
Classifier: Operating System :: OS Independent
Classifier: Development Status :: 3 - Alpha
Classifier: Intended Audience :: Developers
Classifier: License :: Freely Distributable
Classifier: License :: OSI Approved :: Apache Software License
Classifier: Topic :: Software Development :: Testing
Classifier: Topic :: Software Development :: Testing :: Mocking
Requires-Python: >=3.6
Requires-Dist: boto3
